dueling_bandit/__init__.py
dueling_bandit/agents.py
dueling_bandit/datasets.py
dueling_bandit/environment.py
dueling_bandit/experiments.py
dueling_bandit/plotting.py
dueling_bandit-0.1.2.dist-info/licenses/LICENSE
dueling_bandit-0.1.2.dist-info/METADATA
dueling_bandit-0.1.2.dist-info/WHEEL
dueling_bandit-0.1.2.dist-info/top_level.txt
dueling_bandit-0.1.2.dist-info/RECORD
