Metadata-Version: 2.4
Name: dueling-bandit
Version: 0.1.2
Summary: A toolkit for preference-based online learning with dueling bandits
Home-page: https://github.com/shailendrabhandari/dueling_bandit
Author: Shailendra
Author-email: shailendra.bhandari@oslomet.no
License: MIT
Classifier: Programming Language :: Python :: 3
Classifier: Programming Language :: Python :: 3.8
Classifier: Programming Language :: Python :: 3.9
Classifier: Programming Language :: Python :: 3.10
Classifier: Programming Language :: Python :: 3.11
Classifier: Operating System :: OS Independent
Classifier: Intended Audience :: Developers
Classifier: Intended Audience :: Science/Research
Classifier: Topic :: Software Development :: Libraries :: Python Modules
Requires-Python: >=3.8
License-File: LICENSE
Requires-Dist: numpy>=1.21.0
Requires-Dist: matplotlib>=3.4.0
Requires-Dist: scipy>=1.7.0
Requires-Dist: pandas>=1.3.0
Dynamic: author
Dynamic: author-email
Dynamic: classifier
Dynamic: description
Dynamic: description-content-type
Dynamic: home-page
Dynamic: license
Dynamic: license-file
Dynamic: requires-dist
Dynamic: requires-python
Dynamic: summary
